superslug.py
superslug-1.0.1.dist-info/DESCRIPTION.rst
superslug-1.0.1.dist-info/METADATA
superslug-1.0.1.dist-info/RECORD
superslug-1.0.1.dist-info/WHEEL
superslug-1.0.1.dist-info/metadata.json
superslug-1.0.1.dist-info/top_level.txt
